setup.py
./legume/__init__.py
./legume/bitfield.py
./legume/bytebuffer.py
./legume/client.py
./legume/connection.py
./legume/exceptions.py
./legume/messages.py
./legume/metrics.py
./legume/netshared.py
./legume/nevent.py
./legume/pingsampler.py
./legume/server.py
./legume/serverpeer.py
./legume/servicelocator.py
./legume/timing.py
./tests/__init__.py
./tests/all_tests.py
./tests/greenbar.py
./tests/test_accept_new_connections.py
./tests/test_api.py
./tests/test_events.py
./tests/test_keepalive.py
./tests/test_latency.py
./tests/test_metrics.py
./tests/test_nevent.py
./tests/test_newmsg.py
./tests/test_pingsampler.py
./tests/test_reliablemsg.py
./tests/test_udp.py
./tests/test_varstring.py
Legume.egg-info/PKG-INFO
Legume.egg-info/SOURCES.txt
Legume.egg-info/dependency_links.txt
Legume.egg-info/top_level.txt